hte_cli/__init__.py
hte_cli/__main__.py
hte_cli/api_client.py
hte_cli/cli.py
hte_cli/config.py
hte_cli/errors.py
hte_cli/events.py
hte_cli/image_utils.py
hte_cli/runner.py
hte_cli/scorers.py
hte_cli/version_check.py
hte_cli-0.2.31.dist-info/METADATA
hte_cli-0.2.31.dist-info/WHEEL
hte_cli-0.2.31.dist-info/entry_points.txt
hte_cli-0.2.31.dist-info/RECORD
