Metadata-Version: 2.4
Name: hte-cli
Version: 0.2.31
Summary: Human Time-to-Completion Evaluation CLI
Project-URL: Homepage, https://github.com/sean-peters-au/lyptus-mono
Author: Lyptus Research
License: MIT
Keywords: cli,cybersecurity,evaluation,human-baseline
Classifier: Development Status :: 3 - Alpha
Classifier: Environment :: Console
Classifier: Intended Audience :: Science/Research
Classifier: License :: OSI Approved :: MIT License
Classifier: Programming Language :: Python :: 3
Classifier: Programming Language :: Python :: 3.11
Classifier: Programming Language :: Python :: 3.12
Requires-Python: >=3.11
Requires-Dist: click>=8.0
Requires-Dist: httpx>=0.24
Requires-Dist: inspect-ai>=0.3.89
Requires-Dist: keyring>=24.0
Requires-Dist: packaging>=21.0
Requires-Dist: platformdirs>=4.0
Requires-Dist: pydantic>=2.0
Requires-Dist: pyyaml>=6.0
Requires-Dist: rich>=13.0
Provides-Extra: dev
Requires-Dist: pexpect>=4.8; extra == 'dev'
Requires-Dist: pytest-asyncio>=0.23; extra == 'dev'
Requires-Dist: pytest>=7.0; extra == 'dev'
Requires-Dist: requests>=2.28; extra == 'dev'
